<annotation>
        <folder>.</folder>
        <filename>050a853e-3884-47b7-8c61-5f0845a7d652_2_aug7.jpg</filename>
        <path>050a853e-3884-47b7-8c61-5f0845a7d652_2_aug7.jpg</path>
        <source>
                <database>Unknown</database>
        </source>
        <size>
                <width>1100</width>
                <height>1100</height>
                <depth>3</depth>
        </size>
 <object>
                <name>soy</name>
                <pose>Unspecified</pose>
                <truncated>0</truncated>
                <difficult>0</difficult>
                <bndbox>
                        <xmin>511</xmin>
                        <ymin>224</ymin>
                        <xmax>684</xmax>
                        <ymax>875</ymax>
                </bndbox>
        </object>
 <object>
                <name>pod</name>
                <pose>Unspecified</pose>
                <truncated>0</truncated>
                <difficult>0</difficult>
                <bndbox>
                        <xmin>568</xmin>
                        <ymin>532</ymin>
                        <xmax>599</xmax>
                        <ymax>563</ymax>
                </bndbox>
        </object>
 <object>
                <name>pod</name>
                <pose>Unspecified</pose>
                <truncated>0</truncated>
                <difficult>0</difficult>
                <bndbox>
                        <xmin>595</xmin>
                        <ymin>631</ymin>
                        <xmax>630</xmax>
                        <ymax>670</ymax>
                </bndbox>
        </object>
 <object>
                <name>pod</name>
                <pose>Unspecified</pose>
                <truncated>0</truncated>
                <difficult>0</difficult>
                <bndbox>
                        <xmin>560</xmin>
                        <ymin>578</ymin>
                        <xmax>592</xmax>
                        <ymax>616</ymax>
                </bndbox>
        </object>
 <object>
                <name>pod</name>
                <pose>Unspecified</pose>
                <truncated>0</truncated>
                <difficult>0</difficult>
                <bndbox>
                        <xmin>575</xmin>
                        <ymin>505</ymin>
                        <xmax>599</xmax>
                        <ymax>540</ymax>
                </bndbox>
        </object>
 <object>
                <name>pod</name>
                <pose>Unspecified</pose>
                <truncated>0</truncated>
                <difficult>0</difficult>
                <bndbox>
                        <xmin>604</xmin>
                        <ymin>505</ymin>
                        <xmax>636</xmax>
                        <ymax>535</ymax>
                </bndbox>
        </object>
 <object>
                <name>pod</name>
                <pose>Unspecified</pose>
                <truncated>0</truncated>
                <difficult>0</difficult>
                <bndbox>
                        <xmin>621</xmin>
                        <ymin>374</ymin>
                        <xmax>657</xmax>
                        <ymax>415</ymax>
                </bndbox>
        </object>
 <object>
                <name>pod</name>
                <pose>Unspecified</pose>
                <truncated>0</truncated>
                <difficult>0</difficult>
                <bndbox>
                        <xmin>617</xmin>
                        <ymin>429</ymin>
                        <xmax>647</xmax>
                        <ymax>459</ymax>
                </bndbox>
        </object>
 <object>
                <name>pod</name>
                <pose>Unspecified</pose>
                <truncated>0</truncated>
                <difficult>0</difficult>
                <bndbox>
                        <xmin>587</xmin>
                        <ymin>417</ymin>
                        <xmax>614</xmax>
                        <ymax>445</ymax>
                </bndbox>
        </object>
 <object>
                <name>pod</name>
                <pose>Unspecified</pose>
                <truncated>0</truncated>
                <difficult>0</difficult>
                <bndbox>
                        <xmin>607</xmin>
                        <ymin>330</ymin>
                        <xmax>643</xmax>
                        <ymax>346</ymax>
                </bndbox>
        </object>
 <object>
                <name>pod</name>
                <pose>Unspecified</pose>
                <truncated>0</truncated>
                <difficult>0</difficult>
                <bndbox>
                        <xmin>620</xmin>
                        <ymin>293</ymin>
                        <xmax>654</xmax>
                        <ymax>310</ymax>
                </bndbox>
        </object>
</annotation>        
