<annotation>
        <folder>.</folder>
        <filename>120b15e2-9d20-4435-9f95-f4b282660073_1_aug6.jpg</filename>
        <path>120b15e2-9d20-4435-9f95-f4b282660073_1_aug6.jpg</path>
        <source>
                <database>Unknown</database>
        </source>
        <size>
                <width>1100</width>
                <height>1100</height>
                <depth>3</depth>
        </size>
 <object>
                <name>soy</name>
                <pose>Unspecified</pose>
                <truncated>0</truncated>
                <difficult>0</difficult>
                <bndbox>
                        <xmin>247</xmin>
                        <ymin>92</ymin>
                        <xmax>617</xmax>
                        <ymax>978</ymax>
                </bndbox>
        </object>
 <object>
                <name>pod</name>
                <pose>Unspecified</pose>
                <truncated>0</truncated>
                <difficult>0</difficult>
                <bndbox>
                        <xmin>307</xmin>
                        <ymin>332</ymin>
                        <xmax>346</xmax>
                        <ymax>359</ymax>
                </bndbox>
        </object>
 <object>
                <name>pod</name>
                <pose>Unspecified</pose>
                <truncated>0</truncated>
                <difficult>0</difficult>
                <bndbox>
                        <xmin>323</xmin>
                        <ymin>254</ymin>
                        <xmax>353</xmax>
                        <ymax>286</ymax>
                </bndbox>
        </object>
 <object>
                <name>pod</name>
                <pose>Unspecified</pose>
                <truncated>0</truncated>
                <difficult>0</difficult>
                <bndbox>
                        <xmin>354</xmin>
                        <ymin>228</ymin>
                        <xmax>394</xmax>
                        <ymax>264</ymax>
                </bndbox>
        </object>
 <object>
                <name>pod</name>
                <pose>Unspecified</pose>
                <truncated>0</truncated>
                <difficult>0</difficult>
                <bndbox>
                        <xmin>428</xmin>
                        <ymin>131</ymin>
                        <xmax>454</xmax>
                        <ymax>166</ymax>
                </bndbox>
        </object>
 <object>
                <name>pod</name>
                <pose>Unspecified</pose>
                <truncated>0</truncated>
                <difficult>0</difficult>
                <bndbox>
                        <xmin>444</xmin>
                        <ymin>184</ymin>
                        <xmax>464</xmax>
                        <ymax>228</ymax>
                </bndbox>
        </object>
 <object>
                <name>pod</name>
                <pose>Unspecified</pose>
                <truncated>0</truncated>
                <difficult>0</difficult>
                <bndbox>
                        <xmin>463</xmin>
                        <ymin>185</ymin>
                        <xmax>485</xmax>
                        <ymax>224</ymax>
                </bndbox>
        </object>
 <object>
                <name>pod</name>
                <pose>Unspecified</pose>
                <truncated>0</truncated>
                <difficult>0</difficult>
                <bndbox>
                        <xmin>538</xmin>
                        <ymin>165</ymin>
                        <xmax>568</xmax>
                        <ymax>194</ymax>
                </bndbox>
        </object>
 <object>
                <name>pod</name>
                <pose>Unspecified</pose>
                <truncated>0</truncated>
                <difficult>0</difficult>
                <bndbox>
                        <xmin>478</xmin>
                        <ymin>328</ymin>
                        <xmax>505</xmax>
                        <ymax>366</ymax>
                </bndbox>
        </object>
 <object>
                <name>pod</name>
                <pose>Unspecified</pose>
                <truncated>0</truncated>
                <difficult>0</difficult>
                <bndbox>
                        <xmin>440</xmin>
                        <ymin>269</ymin>
                        <xmax>473</xmax>
                        <ymax>312</ymax>
                </bndbox>
        </object>
 <object>
                <name>pod</name>
                <pose>Unspecified</pose>
                <truncated>0</truncated>
                <difficult>0</difficult>
                <bndbox>
                        <xmin>400</xmin>
                        <ymin>321</ymin>
                        <xmax>434</xmax>
                        <ymax>361</ymax>
                </bndbox>
        </object>
 <object>
                <name>pod</name>
                <pose>Unspecified</pose>
                <truncated>0</truncated>
                <difficult>0</difficult>
                <bndbox>
                        <xmin>417</xmin>
                        <ymin>438</ymin>
                        <xmax>452</xmax>
                        <ymax>469</ymax>
                </bndbox>
        </object>
 <object>
                <name>pod</name>
                <pose>Unspecified</pose>
                <truncated>0</truncated>
                <difficult>0</difficult>
                <bndbox>
                        <xmin>508</xmin>
                        <ymin>483</ymin>
                        <xmax>543</xmax>
                        <ymax>534</ymax>
                </bndbox>
        </object>
 <object>
                <name>pod</name>
                <pose>Unspecified</pose>
                <truncated>0</truncated>
                <difficult>0</difficult>
                <bndbox>
                        <xmin>417</xmin>
                        <ymin>519</ymin>
                        <xmax>452</xmax>
                        <ymax>551</ymax>
                </bndbox>
        </object>
 <object>
                <name>pod</name>
                <pose>Unspecified</pose>
                <truncated>0</truncated>
                <difficult>0</difficult>
                <bndbox>
                        <xmin>364</xmin>
                        <ymin>581</ymin>
                        <xmax>403</xmax>
                        <ymax>646</ymax>
                </bndbox>
        </object>
 <object>
                <name>pod</name>
                <pose>Unspecified</pose>
                <truncated>0</truncated>
                <difficult>0</difficult>
                <bndbox>
                        <xmin>541</xmin>
                        <ymin>574</ymin>
                        <xmax>571</xmax>
                        <ymax>621</ymax>
                </bndbox>
        </object>
 <object>
                <name>pod</name>
                <pose>Unspecified</pose>
                <truncated>0</truncated>
                <difficult>0</difficult>
                <bndbox>
                        <xmin>549</xmin>
                        <ymin>472</ymin>
                        <xmax>575</xmax>
                        <ymax>504</ymax>
                </bndbox>
        </object>
 <object>
                <name>pod</name>
                <pose>Unspecified</pose>
                <truncated>0</truncated>
                <difficult>0</difficult>
                <bndbox>
                        <xmin>341</xmin>
                        <ymin>494</ymin>
                        <xmax>375</xmax>
                        <ymax>553</ymax>
                </bndbox>
        </object>
</annotation>        
