<annotation>
        <folder>.</folder>
        <filename>34f0b560-df9f-4be8-8a73-55b82371abd0_1_aug4.jpg</filename>
        <path>34f0b560-df9f-4be8-8a73-55b82371abd0_1_aug4.jpg</path>
        <source>
                <database>Unknown</database>
        </source>
        <size>
                <width>1100</width>
                <height>1100</height>
                <depth>3</depth>
        </size>
 <object>
                <name>soy</name>
                <pose>Unspecified</pose>
                <truncated>0</truncated>
                <difficult>0</difficult>
                <bndbox>
                        <xmin>450</xmin>
                        <ymin>207</ymin>
                        <xmax>579</xmax>
                        <ymax>672</ymax>
                </bndbox>
        </object>
 <object>
                <name>pod</name>
                <pose>Unspecified</pose>
                <truncated>0</truncated>
                <difficult>0</difficult>
                <bndbox>
                        <xmin>537</xmin>
                        <ymin>456</ymin>
                        <xmax>549</xmax>
                        <ymax>485</ymax>
                </bndbox>
        </object>
 <object>
                <name>pod</name>
                <pose>Unspecified</pose>
                <truncated>0</truncated>
                <difficult>0</difficult>
                <bndbox>
                        <xmin>506</xmin>
                        <ymin>407</ymin>
                        <xmax>522</xmax>
                        <ymax>421</ymax>
                </bndbox>
        </object>
 <object>
                <name>pod</name>
                <pose>Unspecified</pose>
                <truncated>0</truncated>
                <difficult>0</difficult>
                <bndbox>
                        <xmin>495</xmin>
                        <ymin>390</ymin>
                        <xmax>505</xmax>
                        <ymax>410</ymax>
                </bndbox>
        </object>
 <object>
                <name>pod</name>
                <pose>Unspecified</pose>
                <truncated>0</truncated>
                <difficult>0</difficult>
                <bndbox>
                        <xmin>500</xmin>
                        <ymin>381</ymin>
                        <xmax>516</xmax>
                        <ymax>392</ymax>
                </bndbox>
        </object>
</annotation>        
