<annotation>
        <folder>.</folder>
        <filename>2b22ec68-9e56-4e4e-9b0e-43f024ef6cb3_1_aug5.jpg</filename>
        <path>2b22ec68-9e56-4e4e-9b0e-43f024ef6cb3_1_aug5.jpg</path>
        <source>
                <database>Unknown</database>
        </source>
        <size>
                <width>1100</width>
                <height>1100</height>
                <depth>3</depth>
        </size>
 <object>
                <name>soy</name>
                <pose>Unspecified</pose>
                <truncated>0</truncated>
                <difficult>0</difficult>
                <bndbox>
                        <xmin>453</xmin>
                        <ymin>228</ymin>
                        <xmax>577</xmax>
                        <ymax>590</ymax>
                </bndbox>
        </object>
 <object>
                <name>pod</name>
                <pose>Unspecified</pose>
                <truncated>0</truncated>
                <difficult>0</difficult>
                <bndbox>
                        <xmin>493</xmin>
                        <ymin>426</ymin>
                        <xmax>505</xmax>
                        <ymax>448</ymax>
                </bndbox>
        </object>
 <object>
                <name>pod</name>
                <pose>Unspecified</pose>
                <truncated>0</truncated>
                <difficult>0</difficult>
                <bndbox>
                        <xmin>503</xmin>
                        <ymin>472</ymin>
                        <xmax>523</xmax>
                        <ymax>502</ymax>
                </bndbox>
        </object>
 <object>
                <name>pod</name>
                <pose>Unspecified</pose>
                <truncated>0</truncated>
                <difficult>0</difficult>
                <bndbox>
                        <xmin>495</xmin>
                        <ymin>463</ymin>
                        <xmax>514</xmax>
                        <ymax>487</ymax>
                </bndbox>
        </object>
 <object>
                <name>pod</name>
                <pose>Unspecified</pose>
                <truncated>0</truncated>
                <difficult>0</difficult>
                <bndbox>
                        <xmin>496</xmin>
                        <ymin>384</ymin>
                        <xmax>520</xmax>
                        <ymax>401</ymax>
                </bndbox>
        </object>
 <object>
                <name>pod</name>
                <pose>Unspecified</pose>
                <truncated>0</truncated>
                <difficult>0</difficult>
                <bndbox>
                        <xmin>508</xmin>
                        <ymin>438</ymin>
                        <xmax>530</xmax>
                        <ymax>454</ymax>
                </bndbox>
        </object>
 <object>
                <name>pod</name>
                <pose>Unspecified</pose>
                <truncated>0</truncated>
                <difficult>0</difficult>
                <bndbox>
                        <xmin>535</xmin>
                        <ymin>461</ymin>
                        <xmax>550</xmax>
                        <ymax>479</ymax>
                </bndbox>
        </object>
 <object>
                <name>pod</name>
                <pose>Unspecified</pose>
                <truncated>0</truncated>
                <difficult>0</difficult>
                <bndbox>
                        <xmin>527</xmin>
                        <ymin>359</ymin>
                        <xmax>548</xmax>
                        <ymax>372</ymax>
                </bndbox>
        </object>
 <object>
                <name>pod</name>
                <pose>Unspecified</pose>
                <truncated>0</truncated>
                <difficult>0</difficult>
                <bndbox>
                        <xmin>525</xmin>
                        <ymin>382</ymin>
                        <xmax>550</xmax>
                        <ymax>396</ymax>
                </bndbox>
        </object>
</annotation>        
