<annotation>
        <folder>.</folder>
        <filename>34f0b560-df9f-4be8-8a73-55b82371abd0_1_aug5.jpg</filename>
        <path>34f0b560-df9f-4be8-8a73-55b82371abd0_1_aug5.jpg</path>
        <source>
                <database>Unknown</database>
        </source>
        <size>
                <width>1100</width>
                <height>1100</height>
                <depth>3</depth>
        </size>
 <object>
                <name>soy</name>
                <pose>Unspecified</pose>
                <truncated>0</truncated>
                <difficult>0</difficult>
                <bndbox>
                        <xmin>404</xmin>
                        <ymin>529</ymin>
                        <xmax>572</xmax>
                        <ymax>915</ymax>
                </bndbox>
        </object>
 <object>
                <name>pod</name>
                <pose>Unspecified</pose>
                <truncated>0</truncated>
                <difficult>0</difficult>
                <bndbox>
                        <xmin>444</xmin>
                        <ymin>739</ymin>
                        <xmax>459</xmax>
                        <ymax>763</ymax>
                </bndbox>
        </object>
 <object>
                <name>pod</name>
                <pose>Unspecified</pose>
                <truncated>0</truncated>
                <difficult>0</difficult>
                <bndbox>
                        <xmin>475</xmin>
                        <ymin>695</ymin>
                        <xmax>497</xmax>
                        <ymax>708</ymax>
                </bndbox>
        </object>
 <object>
                <name>pod</name>
                <pose>Unspecified</pose>
                <truncated>0</truncated>
                <difficult>0</difficult>
                <bndbox>
                        <xmin>498</xmin>
                        <ymin>680</ymin>
                        <xmax>510</xmax>
                        <ymax>697</ymax>
                </bndbox>
        </object>
 <object>
                <name>pod</name>
                <pose>Unspecified</pose>
                <truncated>0</truncated>
                <difficult>0</difficult>
                <bndbox>
                        <xmin>480</xmin>
                        <ymin>673</ymin>
                        <xmax>502</xmax>
                        <ymax>683</ymax>
                </bndbox>
        </object>
</annotation>        
